Metadata-Version: 2.1
Name: collapsible-table
Version: 0.0.1
Summary: Project Description
Home-page: UNKNOWN
Author: xin <hcyxl1@nottingham.ac.uk>
License: MIT
Platform: UNKNOWN
Classifier: Framework :: Dash
License-File: LICENSE
